rdeepl.py
rdeepl-2.0.0.dist-info/licenses/LICENSE.txt
rdeepl-2.0.0.dist-info/METADATA
rdeepl-2.0.0.dist-info/WHEEL
rdeepl-2.0.0.dist-info/top_level.txt
rdeepl-2.0.0.dist-info/RECORD
