Metadata-Version: 2.4
Name: rdeepl
Version: 2.0.0
Summary: deep
Author-email: rxy <1302553960@qq.com>
Classifier: Programming Language :: Python :: 3
Classifier: License :: OSI Approved :: MIT License
Classifier: Operating System :: OS Independent
Requires-Python: >=3.5
License-File: LICENSE.txt
Requires-Dist: openai
Dynamic: license-file
